appflow_patterns/__init__.py
appflow_patterns/py.typed
appflow_patterns/_jsii/__init__.py
appflow_patterns/_jsii/appflow-patterns@0.0.2.jsii.tgz
appflow_patterns-0.0.2.dist-info/LICENSE
appflow_patterns-0.0.2.dist-info/METADATA
appflow_patterns-0.0.2.dist-info/WHEEL
appflow_patterns-0.0.2.dist-info/top_level.txt
appflow_patterns-0.0.2.dist-info/RECORD
